yokadi/__init__.py
yokadi/createdemodb.py
yokadi/yokadid.py
yokadi/core/__init__.py
yokadi/core/basepaths.py
yokadi/core/bugutils.py
yokadi/core/daemon.py
yokadi/core/db.py
yokadi/core/dbutils.py
yokadi/core/fileutils.py
yokadi/core/recurrencerule.py
yokadi/core/ydateutils.py
yokadi/core/yokadiexception.py
yokadi/core/yokadioptionparser.py
yokadi/tests/aliastestcase.py
yokadi/tests/argstestcase.py
yokadi/tests/basepathstestcase.py
yokadi/tests/bugtestcase.py
yokadi/tests/completerstestcase.py
yokadi/tests/conftestcase.py
yokadi/tests/dbtestcase.py
yokadi/tests/dbutilstestcase.py
yokadi/tests/helptestcase.py
yokadi/tests/icaltestcase.py
yokadi/tests/keywordfiltertestcase.py
yokadi/tests/keywordtestcase.py
yokadi/tests/massedittestcase.py
yokadi/tests/parseutilstestcase.py
yokadi/tests/projecttestcase.py
yokadi/tests/recurrenceruletestcase.py
yokadi/tests/tasktestcase.py
yokadi/tests/tests.py
yokadi/tests/testutils.py
yokadi/tests/textlistrenderertestcase.py
yokadi/tests/tuitestcase.py
yokadi/tests/ydateutilstestcase.py
yokadi/tests/yokadioptionparsertestcase.py
yokadi/tests/yokaditestcase.py
yokadi/update/update.py
yokadi/update/update10to11.py
yokadi/update/update11to12.py
yokadi/update/update1to2.py
yokadi/update/update2to3.py
yokadi/update/update3to4.py
yokadi/update/update4to5.py
yokadi/update/update5to6.py
yokadi/update/update6to7.py
yokadi/update/update7to8.py
yokadi/update/update8to9.py
yokadi/update/update9to10.py
yokadi/update/updateutils.py
yokadi/ycli/__init__.py
yokadi/ycli/aliascmd.py
yokadi/ycli/basicparseutils.py
yokadi/ycli/colors.py
yokadi/ycli/commonargs.py
yokadi/ycli/completers.py
yokadi/ycli/confcmd.py
yokadi/ycli/csvlistrenderer.py
yokadi/ycli/htmllistrenderer.py
yokadi/ycli/keywordcmd.py
yokadi/ycli/main.py
yokadi/ycli/massedit.py
yokadi/ycli/parseutils.py
yokadi/ycli/plainlistrenderer.py
yokadi/ycli/projectcmd.py
yokadi/ycli/taskcmd.py
yokadi/ycli/textlistrenderer.py
yokadi/ycli/tui.py
yokadi/ycli/xmllistrenderer.py
yokadi/yical/__init__.py
yokadi-1.3.0.dist-info/LICENSE
yokadi-1.3.0.dist-info/METADATA
yokadi-1.3.0.dist-info/WHEEL
yokadi-1.3.0.dist-info/top_level.txt
yokadi-1.3.0.dist-info/RECORD
